tinycloud/__init__.py
tinycloud/acl.py
tinycloud/app.py
tinycloud/auth_pam.py
tinycloud/auth_pass.py
tinycloud/confmgr.py
tinycloud/dav.py
tinycloud/exceptions.py
tinycloud/mod_manger.py
tinycloud/setup.py
tinycloud/share.py
tinycloud/utils.py
tinycloud/vfs.py
tinycloud/conf/acl.yaml
tinycloud/conf/config.yaml
tinycloud/conf/shares.json
tinycloud/fs/.fs_ftp.py.swo
tinycloud/fs/__init__.py
tinycloud/fs/fs_ftp.py
tinycloud/fs/fs_local.py
tinycloud/fs/fs_syshome.py
tinycloud/static/filelist-070e76aa.js
tinycloud/static/filelist-1e64d4d1.js
tinycloud/static/filelist-1f1c1885.js
tinycloud/static/filelist-2fedbd08.js
tinycloud/static/filelist-36810baf.js
tinycloud/static/filelist-3e192c23.js
tinycloud/static/filelist-3ea520ee.js
tinycloud/static/filelist-417adf50.js
tinycloud/static/filelist-4c10c2e3.js
tinycloud/static/filelist-5a579a9a.js
tinycloud/static/filelist-6e4e6322.js
tinycloud/static/filelist-847cb7c3.js
tinycloud/static/filelist-86839e69.js
tinycloud/static/filelist-873b3223.js
tinycloud/static/filelist-88c2ff80.js
tinycloud/static/filelist-8b43251a.js
tinycloud/static/filelist-8eec0a00.js
tinycloud/static/filelist-ad313528.js
tinycloud/static/filelist-b695496d.js
tinycloud/static/filelist-ce8630b4.js
tinycloud/static/filelist-dfaab1cd.js
tinycloud/static/filelist-ebab8627.js
tinycloud/static/filelist-efa526b8.js
tinycloud/static/filelist-f3b60929.js
tinycloud/static/filelist-f47a2f76.js
tinycloud/static/filelist-f4bc02f0.js
tinycloud/static/index.html
tinycloud/static/index.js
tinycloud/static/share.html
tinycloud/static/share.js
tinycloud/static/assets/common-ff30deda.css
tinycloud/static/assets/webcomponents-loader-97836d09.js
tinycloud/static/locale/en.js
tinycloud/static/locale/zh-CN.js
tinycloud/static/locale/zh-Hans.js
tinycloud/templates/dav_respone
tinycloud-0.1.202209062022.dist-info/LICENSE
tinycloud-0.1.202209062022.dist-info/METADATA
tinycloud-0.1.202209062022.dist-info/WHEEL
tinycloud-0.1.202209062022.dist-info/entry_points.txt
tinycloud-0.1.202209062022.dist-info/top_level.txt
tinycloud-0.1.202209062022.dist-info/RECORD
