Metadata-Version: 2.1
Name: tinycloud
Version: 0.1.202209062022
Maintainer: Lin calvin
Maintainer-email: calvinchaochao@outlook.com
Requires-Python: >=3.7
License-File: LICENSE
Requires-Dist: Flask (>=2.0.3)
Requires-Dist: pam
Requires-Dist: python-pam
Requires-Dist: python-dateutil
Requires-Dist: gevent
